setup.cfg
setup.py
instasent/__init__.py
instasent/client.py
instasent.egg-info/PKG-INFO
instasent.egg-info/SOURCES.txt
instasent.egg-info/dependency_links.txt
instasent.egg-info/requires.txt
instasent.egg-info/top_level.txt