Metadata-Version: 1.1
Name: instasent
Version: 0.1.3
Summary: Instasent's REST API
Home-page: https://github.com/instasent/instasent-python-lib
Author: Instasent
Author-email: support@instasent.com
License: UNKNOWN
Download-URL: https://github.com/instasent/instasent-python-lib/archive/master.zip
Keywords: instasent,sms
Platform: UNKNOWN
